Metadata-Version: 2.1
Name: sage-euler-product
Version: 0.0.1
Summary: Euler Product perform number theorie of euler product
Home-page: https://github.com/archimede-institut/sage-euler-product
Author: Olivier Ramaré, Dominique Benielli
Author-email: dominique.benielli@univ-amu.fr
License: GPLv3.0
Keywords: SageMath Euler Product Number Theory
Classifier: Development Status :: 4 - Beta
Classifier: Intended Audience :: Science/Research
Classifier: Topic :: Software Development :: Build Tools
Classifier: Topic :: Scientific/Engineering :: Mathematics
Classifier: License :: OSI Approved :: GNU General Public License v3 or later (GPLv3+)
Classifier: Programming Language :: Python :: 3.8
License-File: LICENSE
